gen3utils/__init__.py
gen3utils/assertion.py
gen3utils/deployment_changes/__init__.py
gen3utils/deployment_changes/generate_comment.py
gen3utils/errors.py
gen3utils/etl/__init__.py
gen3utils/etl/dd_utils.py
gen3utils/etl/etl_validator.py
gen3utils/gitops/__init__.py
gen3utils/gitops/gitops_validator.py
gen3utils/main.py
gen3utils/manifest/__init__.py
gen3utils/manifest/manifest_validator.py
gen3utils/manifest/validation_config.yaml
gen3utils/s3log/s3log.py
gen3utils/s3log/s3log_worker.py
gen3utils/utils.py
gen3utils-1.0.0.dist-info/METADATA
gen3utils-1.0.0.dist-info/WHEEL
gen3utils-1.0.0.dist-info/entry_points.txt
gen3utils-1.0.0.dist-info/licenses/LICENSE
gen3utils-1.0.0.dist-info/licenses/NOTICE
gen3utils-1.0.0.dist-info/RECORD
