Metadata-Version: 2.4
Name: gen3utils
Version: 1.0.0
Summary: Utils for Gen3 Commons management
License: Apache-2.0
License-File: LICENSE
License-File: NOTICE
Author: CTDS UChicago
Author-email: cdis@uchicago.edu
Requires-Python: >=3.13,<4
Classifier: License :: OSI Approved :: Apache Software License
Classifier: Programming Language :: Python :: 3
Classifier: Programming Language :: Python :: 3.13
Classifier: Programming Language :: Python :: 3.14
Requires-Dist: aiobotocore (>=3.1.0,<4.0.0)
Requires-Dist: cdislogging (>=1,<2)
Requires-Dist: click (>=8,<9)
Requires-Dist: dictionaryutils (>=4,<5)
Requires-Dist: gen3datamodel (>=4,<5)
Requires-Dist: gen3git (>=0.7.0,<1.0.0)
Project-URL: Repository, https://github.com/uc-cdis/gen3utils
